rgrow-0.21.1.dist-info/METADATA
rgrow-0.21.1.dist-info/WHEEL
rgrow-0.21.1.dist-info/licenses/LICENSE
rgrow/__init__.py
rgrow/kblock.py
rgrow/kblock.pyi
rgrow/py.typed
rgrow/rgrow-gui
rgrow/rgrow.pyd
rgrow/rgrow.pyi
rgrow/sdc/__init__.py
rgrow/sdc/anneal.py
rgrow/sdc/graphs.py
rgrow/sdc/reporter_methods/__init__.py
rgrow/sdc/reporter_methods/base.py
rgrow/sdc/reporter_methods/fluorescence.py
rgrow/sdc/reporter_methods/last_compute.py
rgrow/sdc/reporter_methods/mfe.py
rgrow/sdc/reporter_methods/reporter_computation.py
rgrow/sdc/reporter_methods/strand_at.py
rgrow/sdc/reporter_methods/target.py
rgrow/sdc/sdc.py
rgrow/sdc/strand.py
rgrow-0.21.1.dist-info/RECORD
