Metadata-Version: 2.4
Name: rgrow
Version: 0.21.1
Requires-Dist: numpy~=2.0
Requires-Dist: attrs~=23.2
Requires-Dist: matplotlib~=3.9
Requires-Dist: typing-extensions
Requires-Dist: tqdm
Requires-Dist: pyyaml
Requires-Dist: platformdirs
Requires-Dist: rgrow-gui
Requires-Dist: patchelf>=0.17.2.4
Requires-Dist: pytest ; extra == 'testing'
Requires-Dist: hypothesis ; extra == 'testing'
Provides-Extra: testing
License-File: LICENSE
Requires-Python: >=3.10
